Workbook

Sheet Dashboard
A1: ✦ CUSTOMER TRANSACTION INTELLIGENCE DASHBOARD
A2: Reporting period | B2: All dates | D2: Region | E2: All regions | G2: Customer segment | H2: All segments
A4: TOTAL REVENUE | D4: TRANSACTIONS | G4: UNITS SOLD | J4: AVG. ORDER VALUE
A5: =Analysis!B4 -> 229192.47 | D5: =Analysis!B5 -> 250 | G5: =Analysis!B6 -> 753 | J5: =Analysis!B7 -> 916.76988
A7: UNIQUE CUSTOMERS | D7: TOP PRODUCT | G7: TOP REGION | J7: MOST FREQUENT PRODUCT
A8: =Analysis!B8 -> 50 | D8: =INDEX(Analysis!A16:A30,MATCH(MAX(Analysis!B16:B30),Analysis!B16:B30,0)) -> Bookshelf | G8: =INDEX(Analysis!G4:G8,MATCH(MAX(Analysis!H4:H8),Analysis!H4:H8,0)) -> East | J8: =INDEX(Analysis!A16:A30,MATCH(MAX(Analysis!D16:D30),Analysis!D16:D30,0)) -> Bookshelf

Sheet Project Instructions
A1: PR. Final Project - "Data Intelligence Dashboard"
A2: Dataset: Use the 'Final Project Dataset' sheet containing 200+ records of customer transactions. Objective: Create a full-fledged analysis and reporting solution using Excel to analyze customer transactions, find insights, and build visualizations and dashboards. Key Topics to Implement: - Date & Time Functions: TODAY, NOW, DATEDIF, EOMONTH - FILTER Function for multi-value returns - Conditional Formatting with Icons/Arrows - Create Timestamp (using NOW and iterative calculations) - WHAT-IF Analysis: Scenario Manager, Goal Seek - Linear Regression using Data Analysis Toolpak - Data Analysis & Storytelling from the dataset - Use GroupBy concepts to find High-Value Customers using formulas - Create Dashboard using: - Pivot Tables - Pivot Charts (Bar, Line, Pie) - Slicers and Timelines - KPI Indicators with Conditional Formatting - Find most frequently purchased product or repeating names using formulas - Compare two lists and extract matching names in a new column - Create Abbreviations using TEXT functions - Build a final report with insights and storytelling Deliverable: - Well-structured workbook with multiple sheets (Raw Data, Analysis, Visualizations, Dashboard) - Summary Insights with key metrics: Total Revenue, Top Customers, Most Sold Products, Regional Sales - Use of all required formulas and functions as listed above

Sheet Raw Data
A1: Transaction_ID | B1: Date | C1: Customer_ID | D1: Customer_Name | E1: Product_ID | F1: Product_Name | G1: Category | H1: Quantity | I1: Unit_Price | J1: Payment_Method | K1: Region | L1: Customer_Segment | M1: Customer_Since | N1: Total_Amount | O1: Month | P1: Year | Q1: Customer_Tenure_Years | R1: Customer_Abbreviation | S1: Transaction_Timestamp
A2: TRX0155 | B2: 45393 | C2: CUST023 | D2: Paul Baker | E2: P009 | F2: Monitor | G2: Electronics | H2: 3 | I2: 249.99 | J2: Cash | K2: Central | L2: Basic | M2: 44425 | N2: 749.97 | O2: =TEXT(B2,"yyyy-mm") -> 2024-04 | P2: =YEAR(B2) -> 2024 | Q2: =DATEDIF(M2,B2,"Y") -> 2 | R2: =UPPER(LEFT(D2,1)&MID(D2,FIND(" ",D2)+1,1)) -> PB | S2: =NOW() -> 46309.658
A3: TRX0023 | B3: 45396 | C3: CUST013 | D3: Joseph Jackson | E3: P009 | F3: Monitor | G3: Electronics | H3: 3 | I3: 249.99 | J3: Credit Card | K3: Central | L3: Premium | M3: 44575 | N3: 749.97 | O3: =TEXT(B3,"yyyy-mm") -> 2024-04 | P3: =YEAR(B3) -> 2024 | Q3: =DATEDIF(M3,B3,"Y") -> 2 | R3: =UPPER(LEFT(D3,1)&MID(D3,FIND(" ",D3)+1,1)) -> JJ | S3: =NOW() -> 46309.658
A4: TRX0139 | B4: 45399 | C4: CUST021 | D4: Kevin Scott | E4: P005 | F4: Blender | G4: Appliances | H4: 3 | I4: 59.99 | J4: PayPal | K4: South | L4: Standard | M4: 45262 | N4: 179.97 | O4: =TEXT(B4,"yyyy-mm") -> 2024-04 | P4: =YEAR(B4) -> 2024 | Q4: =DATEDIF(M4,B4,"Y") -> 0 | R4: =UPPER(LEFT(D4,1)&MID(D4,FIND(" ",D4)+1,1)) -> KS | S4: =NOW() -> 46309.658
A5: TRX0043 | B5: 45400 | C5: CUST046 | D5: Kathleen Bennett | E5: P005 | F5: Blender | G5: Appliances | H5: 3 | I5: 59.99 | J5: Cash | K5: North | L5: Premium | M5: 45114 | N5: 179.97 | O5: =TEXT(B5,"yyyy-mm") -> 2024-04 | P5: =YEAR(B5) -> 2024 | Q5: =DATEDIF(M5,B5,"Y") -> 0 | R5: =UPPER(LEFT(D5,1)&MID(D5,FIND(" ",D5)+1,1)) -> KB | S5: =NOW() -> 46309.658
A6: TRX0212 | B6: 45400 | C6: CUST003 | D6: Michael Brown | E6: P008 | F6: Bookshelf | G6: Furniture | H6: 5 | I6: 149.99 | J6: Credit Card | K6: North | L6: Premium | M6: 45295 | N6: 749.95 | O6: =TEXT(B6,"yyyy-mm") -> 2024-04 | P6: =YEAR(B6) -> 2024 | Q6: =DATEDIF(M6,B6,"Y") -> 0 | R6: =UPPER(LEFT(D6,1)&MID(D6,FIND(" ",D6)+1,1)) -> MB | S6: =NOW() -> 46309.658
A7: TRX0092 | B7: 45403 | C7: CUST024 | D7: Dorothy Nelson | E7: P005 | F7: Blender | G7: Appliances | H7: 2 | I7: 59.99 | J7: Cash | K7: West | L7: Standard | M7: 44746 | N7: 119.98 | O7: =TEXT(B7,"yyyy-mm") -> 2024-04 | P7: =YEAR(B7) -> 2024 | Q7: =DATEDIF(M7,B7,"Y") -> 1 | R7: =UPPER(LEFT(D7,1)&MID(D7,FIND(" ",D7)+1,1)) -> DN | S7: =NOW() -> 46309.658
A8: TRX0193 | B8: 45403 | C8: CUST024 | D8: Dorothy Nelson | E8: P003 | F8: Headphones | G8: Electronics | H8: 5 | I8: 149.99 | J8: Credit Card | K8: Central | L8: Standard | M8: 44418 | N8: 749.95 | O8: =TEXT(B8,"yyyy-mm") -> 2024-04 | P8: =YEAR(B8) -> 2024 | Q8: =DATEDIF(M8,B8,"Y") -> 2 | R8: =UPPER(LEFT(D8,1)&MID(D8,FIND(" ",D8)+1,1)) -> DN | S8: =NOW() -> 46309.658
A9: TRX0240 | B9: 45403 | C9: CUST017 | D9: Charles Allen | E9: P005 | F9: Blender | G9: Appliances | H9: 3 | I9: 59.99 | J9: Debit Card | K9: South | L9: Basic | M9: 45007 | N9: 179.97 | O9: =TEXT(B9,"yyyy-mm") -> 2024-04 | P9: =YEAR(B9) -> 2024 | Q9: =DATEDIF(M9,B9,"Y") -> 1 | R9: =UPPER(LEFT(D9,1)&MID(D9,FIND(" ",D9)+1,1)) -> CA | S9: =NOW() -> 46309.658
A10: TRX0135 | B10: 45405 | C10: CUST009 | D10: Robert Thomas | E10: P001 | F10: Laptop | G10: Electronics | H10: 3 | I10: 899.99 | J10: PayPal | K10: East | L10: Standard | M10: 45299 | N10: 2699.97 | O10: =TEXT(B10,"yyyy-mm") -> 2024-04 | P10: =YEAR(B10) -> 2024 | Q10: =DATEDIF(M10,B10,"Y") -> 0 | R10: =UPPER(LEFT(D10,1)&MID(D10,FIND(" ",D10)+1,1)) -> RT | S10: =NOW() -> 46309.658
A11: TRX0185 | B11: 45408 | C11: CUST026 | D11: Karen Hill | E11: P005 | F11: Blender | G11: Appliances | H11: 3 | I11: 59.99 | J11: Cash | K11: West | L11: Premium | M11: 45207 | N11: 179.97 | O11: =TEXT(B11,"yyyy-mm") -> 2024-04 | P11: =YEAR(B11) -> 2024 | Q11: =DATEDIF(M11,B11,"Y") -> 0 | R11: =UPPER(LEFT(D11,1)&MID(D11,FIND(" ",D11)+1,1)) -> KH | S11: =NOW() -> 46309.658
A12: TRX0138 | B12: 45408 | C12: CUST022 | D12: Susan Green | E12: P008 | F12: Bookshelf | G12: Furniture | H12: 1 | I12: 149.99 | J12: Credit Card | K12: West | L12: Standard | M12: 45103 | N12: 149.99 | O12: =TEXT(B12,"yyyy-mm") -> 2024-04 | P12: =YEAR(B12) -> 2024 | Q12: =DATEDIF(M12,B12,"Y") -> 0 | R12: =UPPER(LEFT(D12,1)&MID(D12,FIND(" ",D12)+1,1)) -> SG | S12: =NOW() -> 46309.658
A13: TRX0209 | B13: 45408 | C13: CUST046 | D13: Kathleen Bennett | E13: P008 | F13: Bookshelf | G13: Furniture | H13: 5 | I13: 149.99 | J13: Debit Card | K13: North | L13: Basic | M13: 44830 | N13: 749.95 | O13: =TEXT(B13,"yyyy-mm") -> 2024-04 | P13: =YEAR(B13) -> 2024 | Q13: =DATEDIF(M13,B13,"Y") -> 1 | R13: =UPPER(LEFT(D13,1)&MID(D13,FIND(" ",D13)+1,1)) -> KB | S13: =NOW() -> 46309.658
... A251: TRX0064 | B251: 45758 | C251: CUST031 | D251: Steven Turner | E251: P010 | F251: Keyboard | G251: Electronics | H251: 3 | I251: 89.99 | J251: Debit Card | K251: North | L251: Premium | M251: 44878 | N251: 269.97 | O251: =TEXT(B251,"yyyy-mm") -> 2025-04 | P251: =YEAR(B251) -> 2025 | Q251: =DATEDIF(M251,B251,"Y") -> 2 | R251: =UPPER(LEFT(D251,1)&MID(D251,FIND(" ",D251)+1,1)) -> ST | S251: =NOW() -> 46309.658

Sheet Analysis
A1: DATA INTELLIGENCE | ANALYSIS
A3: Core KPI | B3: Value | D3: Category | E3: Revenue | G3: Region | H3: Revenue | J3: Month | K3: Revenue | L3: Transactions
A4: Total Revenue | B4: =SUM('Raw Data'!N2:N251) -> 229192.47 | D4: Appliances | E4: =SUMIF('Raw Data'!G$2:G$251,D4,'Raw Data'!N$2:N$251) -> 8338.74 | G4: Central | H4: =SUMIF('Raw Data'!K$2:K$251,G4,'Raw Data'!N$2:N$251) -> 41288.34 | J4: 2024-04 | K4: =SUMIF('Raw Data'!O$2:O$251,J4,'Raw Data'!N$2:N$251) -> 20919.33 | L4: =COUNTIF('Raw Data'!O$2:O$251,J4) -> 21
A5: Total Transactions | B5: =COUNTA('Raw Data'!A2:A251) -> 250 | D5: Electronics | E5: =SUMIF('Raw Data'!G$2:G$251,D5,'Raw Data'!N$2:N$251) -> 171756.05 | G5: East | H5: =SUMIF('Raw Data'!K$2:K$251,G5,'Raw Data'!N$2:N$251) -> 59288.39 | J5: 2024-05 | K5: =SUMIF('Raw Data'!O$2:O$251,J5,'Raw Data'!N$2:N$251) -> 17039.35 | L5: =COUNTIF('Raw Data'!O$2:O$251,J5) -> 19
A6: Units Sold | B6: =SUM('Raw Data'!H2:H251) -> 753 | D6: Furniture | E6: =SUMIF('Raw Data'!G$2:G$251,D6,'Raw Data'!N$2:N$251) -> 49097.68 | G6: North | H6: =SUMIF('Raw Data'!K$2:K$251,G6,'Raw Data'!N$2:N$251) -> 50808.31 | J6: 2024-06 | K6: =SUMIF('Raw Data'!O$2:O$251,J6,'Raw Data'!N$2:N$251) -> 19299.45 | L6: =COUNTIF('Raw Data'!O$2:O$251,J6) -> 19
A7: Average Transaction | B7: =AVERAGE('Raw Data'!N2:N251) -> 916.76988 | G7: South | H7: =SUMIF('Raw Data'!K$2:K$251,G7,'Raw Data'!N$2:N$251) -> 36398.75 | J7: 2024-07 | K7: =SUMIF('Raw Data'!O$2:O$251,J7,'Raw Data'!N$2:N$251) -> 18479.4 | L7: =COUNTIF('Raw Data'!O$2:O$251,J7) -> 24
A8: Unique Customers | B8: =SUMPRODUCT(('Raw Data'!C2:C251<>"")/COUNTIF('Raw Data'!C2:C251,'Raw Data'!C2:C251&"")) -> 50 | G8: West | H8: =SUMIF('Raw Data'!K$2:K$251,G8,'Raw Data'!N$2:N$251) -> 41408.68 | J8: 2024-08 | K8: =SUMIF('Raw Data'!O$2:O$251,J8,'Raw Data'!N$2:N$251) -> 15759.43 | L8: =COUNTIF('Raw Data'!O$2:O$251,J8) -> 18
A9: Latest Transaction | B9: =MAX('Raw Data'!B2:B251) -> 45758 | J9: 2024-09 | K9: =SUMIF('Raw Data'!O$2:O$251,J9,'Raw Data'!N$2:N$251) -> 12989.51 | L9: =COUNTIF('Raw Data'!O$2:O$251,J9) -> 19
A10: Report Date | B10: =TODAY() -> 46309 | J10: 2024-10 | K10: =SUMIF('Raw Data'!O$2:O$251,J10,'Raw Data'!N$2:N$251) -> 20609.52 | L10: =COUNTIF('Raw Data'!O$2:O$251,J10) -> 16
A11: Current Date-Time | B11: =NOW() -> 46309.658 | J11: 2024-11 | K11: =SUMIF('Raw Data'!O$2:O$251,J11,'Raw Data'!N$2:N$251) -> 12309.44 | L11: =COUNTIF('Raw Data'!O$2:O$251,J11) -> 17
J12: 2024-12 | K12: =SUMIF('Raw Data'!O$2:O$251,J12,'Raw Data'!N$2:N$251) -> 23039.3 | L12: =COUNTIF('Raw Data'!O$2:O$251,J12) -> 25
J13: 2025-01 | K13: =SUMIF('Raw Data'!O$2:O$251,J13,'Raw Data'!N$2:N$251) -> 25799.15 | L13: =COUNTIF('Raw Data'!O$2:O$251,J13) -> 26
J14: 2025-02 | K14: =SUMIF('Raw Data'!O$2:O$251,J14,'Raw Data'!N$2:N$251) -> 16069.38 | L14: =COUNTIF('Raw Data'!O$2:O$251,J14) -> 20
A15: Product | B15: Units Sold | C15: Revenue | D15: Transaction Count | F15: Customer | G15: Transactions | H15: Revenue | J15: 2025-03 | K15: =SUMIF('Raw Data'!O$2:O$251,J15,'Raw Data'!N$2:N$251) -> 19899.38 | L15: =COUNTIF('Raw Data'!O$2:O$251,J15) -> 19
A16: Blender | B16: =SUMIF('Raw Data'!F$2:F$251,A16,'Raw Data'!H$2:H$251) -> 87 | C16: =SUMIF('Raw Data'!F$2:F$251,A16,'Raw Data'!N$2:N$251) -> 5219.13 | D16: =COUNTIF('Raw Data'!F$2:F$251,A16) -> 29 | F16: Mark Carter | G16: =COUNTIF('Raw Data'!D$2:D$251,F16) -> 12 | H16: =SUMIF('Raw Data'!D$2:D$251,F16,'Raw Data'!N$2:N$251) -> 15659.65 | J16: 2025-04 | K16: =SUMIF('Raw Data'!O$2:O$251,J16,'Raw Data'!N$2:N$251) -> 6979.83 | L16: =COUNTIF('Raw Data'!O$2:O$251,J16) -> 7
A17: Bookshelf | B17: =SUMIF('Raw Data'!F$2:F$251,A17,'Raw Data'!H$2:H$251) -> 102 | C17: =SUMIF('Raw Data'!F$2:F$251,A17,'Raw Data'!N$2:N$251) -> 15298.98 | D17: =COUNTIF('Raw Data'!F$2:F$251,A17) -> 35 | F17: Edward Mitchell | G17: =COUNTIF('Raw Data'!D$2:D$251,F17) -> 6 | H17: =SUMIF('Raw Data'!D$2:D$251,F17,'Raw Data'!N$2:N$251) -> 11919.77
A18: Coffee Maker | B18: =SUMIF('Raw Data'!F$2:F$251,A18,'Raw Data'!H$2:H$251) -> 39 | C18: =SUMIF('Raw Data'!F$2:F$251,A18,'Raw Data'!N$2:N$251) -> 3119.61 | D18: =COUNTIF('Raw Data'!F$2:F$251,A18) -> 14 | F18: Barbara Young | G18: =COUNTIF('Raw Data'!D$2:D$251,F18) -> 5 | H18: =SUMIF('Raw Data'!D$2:D$251,F18,'Raw Data'!N$2:N$251) -> 10649.8
A19: Desk | B19: =SUMIF('Raw Data'!F$2:F$251,A19,'Raw Data'!H$2:H$251) -> 78 | C19: =SUMIF('Raw Data'!F$2:F$251,A19,'Raw Data'!N$2:N$251) -> 23399.22 | D19: =COUNTIF('Raw Data'!F$2:F$251,A19) -> 26 | F19: Patricia Moore | G19: =COUNTIF('Raw Data'!D$2:D$251,F19) -> 8 | H19: =SUMIF('Raw Data'!D$2:D$251,F19,'Raw Data'!N$2:N$251) -> 9799.73
A20: Headphones | B20: =SUMIF('Raw Data'!F$2:F$251,A20,'Raw Data'!H$2:H$251) -> 47 | C20: =SUMIF('Raw Data'!F$2:F$251,A20,'Raw Data'!N$2:N$251) -> 7049.53 | D20: =COUNTIF('Raw Data'!F$2:F$251,A20) -> 16 | F20: Paul Baker | G20: =COUNTIF('Raw Data'!D$2:D$251,F20) -> 8 | H20: =SUMIF('Raw Data'!D$2:D$251,F20,'Raw Data'!N$2:N$251) -> 8309.74
A21: Keyboard | B21: =SUMIF('Raw Data'!F$2:F$251,A21,'Raw Data'!H$2:H$251) -> 89 | C21: =SUMIF('Raw Data'!F$2:F$251,A21,'Raw Data'!N$2:N$251) -> 8009.11 | D21: =COUNTIF('Raw Data'!F$2:F$251,A21) -> 34 | F21: Dorothy Nelson | G21: =COUNTIF('Raw Data'!D$2:D$251,F21) -> 6 | H21: =SUMIF('Raw Data'!D$2:D$251,F21,'Raw Data'!N$2:N$251) -> 8269.79
A22: Laptop | B22: =SUMIF('Raw Data'!F$2:F$251,A22,'Raw Data'!H$2:H$251) -> 75 | C22: =SUMIF('Raw Data'!F$2:F$251,A22,'Raw Data'!N$2:N$251) -> 67499.25 | D22: =COUNTIF('Raw Data'!F$2:F$251,A22) -> 24 | F22: Karen Hill | G22: =COUNTIF('Raw Data'!D$2:D$251,F22) -> 8 | H22: =SUMIF('Raw Data'!D$2:D$251,F22,'Raw Data'!N$2:N$251) -> 8009.77
A23: Monitor | B23: =SUMIF('Raw Data'!F$2:F$251,A23,'Raw Data'!H$2:H$251) -> 88 | C23: =SUMIF('Raw Data'!F$2:F$251,A23,'Raw Data'!N$2:N$251) -> 21999.12 | D23: =COUNTIF('Raw Data'!F$2:F$251,A23) -> 26 | F23: Daniel King | G23: =COUNTIF('Raw Data'!D$2:D$251,F23) -> 7 | H23: =SUMIF('Raw Data'!D$2:D$251,F23,'Raw Data'!N$2:N$251) -> 7309.8
A24: Office Chair | B24: =SUMIF('Raw Data'!F$2:F$251,A24,'Raw Data'!H$2:H$251) -> 52 | C24: =SUMIF('Raw Data'!F$2:F$251,A24,'Raw Data'!N$2:N$251) -> 10399.48 | D24: =COUNTIF('Raw Data'!F$2:F$251,A24) -> 15 | F24: Lawrence Reed | G24: =COUNTIF('Raw Data'!D$2:D$251,F24) -> 8 | H24: =SUMIF('Raw Data'!D$2:D$251,F24,'Raw Data'!N$2:N$251) -> 6989.77
A25: Smartphone | B25: =SUMIF('Raw Data'!F$2:F$251,A25,'Raw Data'!H$2:H$251) -> 96 | C25: =SUMIF('Raw Data'!F$2:F$251,A25,'Raw Data'!N$2:N$251) -> 67199.04 | D25: =COUNTIF('Raw Data'!F$2:F$251,A25) -> 31 | F25: Joseph Jackson | G25: =COUNTIF('Raw Data'!D$2:D$251,F25) -> 5 | H25: =SUMIF('Raw Data'!D$2:D$251,F25,'Raw Data'!N$2:N$251) -> 6949.84
F26: Helen Roberts | G26: =COUNTIF('Raw Data'!D$2:D$251,F26) -> 7 | H26: =SUMIF('Raw Data'!D$2:D$251,F26,'Raw Data'!N$2:N$251) -> 6459.79
F27: Gerald Murphy | G27: =COUNTIF('Raw Data'!D$2:D$251,F27) -> 4 | H27: =SUMIF('Raw Data'!D$2:D$251,F27,'Raw Data'!N$2:N$251) -> 6379.87
F28: Sandra Phillips | G28: =COUNTIF('Raw Data'!D$2:D$251,F28) -> 5 | H28: =SUMIF('Raw Data'!D$2:D$251,F28,'Raw Data'!N$2:N$251) -> 6349.83
F29: Michael Brown | G29: =COUNTIF('Raw Data'!D$2:D$251,F29) -> 9 | H29: =SUMIF('Raw Data'!D$2:D$251,F29,'Raw Data'!N$2:N$251) -> 6169.74
F30: Peter Richardson | G30: =COUNTIF('Raw Data'!D$2:D$251,F30) -> 5 | H30: =SUMIF('Raw Data'!D$2:D$251,F30,'Raw Data'!N$2:N$251) -> 5949.85
F31: Betty Campbell | G31: =COUNTIF('Raw Data'!D$2:D$251,F31) -> 5 | H31: =SUMIF('Raw Data'!D$2:D$251,F31,'Raw Data'!N$2:N$251) -> 5649.84
F32: Sharon Butler | G32: =COUNTIF('Raw Data'!D$2:D$251,F32) -> 6 | H32: =SUMIF('Raw Data'!D$2:D$251,F32,'Raw Data'!N$2:N$251) -> 5619.87
F33: Harry Morgan | G33: =COUNTIF('Raw Data'!D$2:D$251,F33) -> 4 | H33: =SUMIF('Raw Data'!D$2:D$251,F33,'Raw Data'!N$2:N$251) -> 5519.89
F34: Sarah Davis | G34: =COUNTIF('Raw Data'!D$2:D$251,F34) -> 5 | H34: =SUMIF('Raw Data'!D$2:D$251,F34,'Raw Data'!N$2:N$251) -> 5499.81
F35: Charles Allen | G35: =COUNTIF('Raw Data'!D$2:D$251,F35) -> 9 | H35: =SUMIF('Raw Data'!D$2:D$251,F35,'Raw Data'!N$2:N$251) -> 5089.73
F36: Douglas Watson | G36: =COUNTIF('Raw Data'!D$2:D$251,F36) -> 4 | H36: =SUMIF('Raw Data'!D$2:D$251,F36,'Raw Data'!N$2:N$251) -> 4829.89
F37: Virginia Sanders | G37: =COUNTIF('Raw Data'!D$2:D$251,F37) -> 6 | H37: =SUMIF('Raw Data'!D$2:D$251,F37,'Raw Data'!N$2:N$251) -> 4789.79
... F65: James Johnson | G65: =COUNTIF('Raw Data'!D$2:D$251,F65) -> 1 | H65: =SUMIF('Raw Data'!D$2:D$251,F65,'Raw Data'!N$2:N$251) -> 179.97

Sheet Pivot Tables
A1: PIVOT TABLES | CUSTOMER TRANSACTION SUMMARY
A5: 1. REVENUE & UNITS BY CATEGORY | E5: 2. PERFORMANCE BY REGION
A6: Category | B6: Total Revenue | C6: Units Sold | D6: Transactions | E6: Region | F6: Total Revenue | G6: Transactions | H6: Avg. Order Value
A7: Appliances | B7: =SUMIF('Raw Data'!$G$2:$G$251,A7,'Raw Data'!$N$2:$N$251) -> 8338.74 | C7: =SUMIF('Raw Data'!$G$2:$G$251,A7,'Raw Data'!$H$2:$H$251) -> 126 | D7: =COUNTIF('Raw Data'!$G$2:$G$251,A7) -> 43 | E7: Central | F7: =SUMIF('Raw Data'!$K$2:$K$251,E7,'Raw Data'!$N$2:$N$251) -> 41288.34 | G7: =COUNTIF('Raw Data'!$K$2:$K$251,E7) -> 54 | H7: =AVERAGEIF('Raw Data'!$K$2:$K$251,E7,'Raw Data'!$N$2:$N$251) -> 764.59889
A8: Electronics | B8: =SUMIF('Raw Data'!$G$2:$G$251,A8,'Raw Data'!$N$2:$N$251) -> 171756.05 | C8: =SUMIF('Raw Data'!$G$2:$G$251,A8,'Raw Data'!$H$2:$H$251) -> 395 | D8: =COUNTIF('Raw Data'!$G$2:$G$251,A8) -> 131 | E8: East | F8: =SUMIF('Raw Data'!$K$2:$K$251,E8,'Raw Data'!$N$2:$N$251) -> 59288.39 | G8: =COUNTIF('Raw Data'!$K$2:$K$251,E8) -> 48 | H8: =AVERAGEIF('Raw Data'!$K$2:$K$251,E8,'Raw Data'!$N$2:$N$251) -> 1235.1748
A9: Furniture | B9: =SUMIF('Raw Data'!$G$2:$G$251,A9,'Raw Data'!$N$2:$N$251) -> 49097.68 | C9: =SUMIF('Raw Data'!$G$2:$G$251,A9,'Raw Data'!$H$2:$H$251) -> 232 | D9: =COUNTIF('Raw Data'!$G$2:$G$251,A9) -> 76 | E9: North | F9: =SUMIF('Raw Data'!$K$2:$K$251,E9,'Raw Data'!$N$2:$N$251) -> 50808.31 | G9: =COUNTIF('Raw Data'!$K$2:$K$251,E9) -> 59 | H9: =AVERAGEIF('Raw Data'!$K$2:$K$251,E9,'Raw Data'!$N$2:$N$251) -> 861.1578
E10: South | F10: =SUMIF('Raw Data'!$K$2:$K$251,E10,'Raw Data'!$N$2:$N$251) -> 36398.75 | G10: =COUNTIF('Raw Data'!$K$2:$K$251,E10) -> 42 | H10: =AVERAGEIF('Raw Data'!$K$2:$K$251,E10,'Raw Data'!$N$2:$N$251) -> 866.6369
E11: West | F11: =SUMIF('Raw Data'!$K$2:$K$251,E11,'Raw Data'!$N$2:$N$251) -> 41408.68 | G11: =COUNTIF('Raw Data'!$K$2:$K$251,E11) -> 47 | H11: =AVERAGEIF('Raw Data'!$K$2:$K$251,E11,'Raw Data'!$N$2:$N$251) -> 881.03574
A14: 3. PRODUCT PERFORMANCE | E14: 4. CUSTOMER SEGMENT
A15: Product | B15: Total Revenue | C15: Units Sold | D15: Transactions | E15: Segment | F15: Total Revenue | G15: Transactions | H15: Avg. Order Value
A16: Blender | B16: =SUMIF('Raw Data'!$F$2:$F$251,A16,'Raw Data'!$N$2:$N$251) -> 5219.13 | C16: =SUMIF('Raw Data'!$F$2:$F$251,A16,'Raw Data'!$H$2:$H$251) -> 87 | D16: =COUNTIF('Raw Data'!$F$2:$F$251,A16) -> 29 | E16: Basic | F16: =SUMIF('Raw Data'!$L$2:$L$251,E16,'Raw Data'!$N$2:$N$251) -> 62177.81 | G16: =COUNTIF('Raw Data'!$L$2:$L$251,E16) -> 74 | H16: =AVERAGEIF('Raw Data'!$L$2:$L$251,E16,'Raw Data'!$N$2:$N$251) -> 840.24068
A17: Bookshelf | B17: =SUMIF('Raw Data'!$F$2:$F$251,A17,'Raw Data'!$N$2:$N$251) -> 15298.98 | C17: =SUMIF('Raw Data'!$F$2:$F$251,A17,'Raw Data'!$H$2:$H$251) -> 102 | D17: =COUNTIF('Raw Data'!$F$2:$F$251,A17) -> 35 | E17: Premium | F17: =SUMIF('Raw Data'!$L$2:$L$251,E17,'Raw Data'!$N$2:$N$251) -> 84657.12 | G17: =COUNTIF('Raw Data'!$L$2:$L$251,E17) -> 95 | H17: =AVERAGEIF('Raw Data'!$L$2:$L$251,E17,'Raw Data'!$N$2:$N$251) -> 891.12758
A18: Coffee Maker | B18: =SUMIF('Raw Data'!$F$2:$F$251,A18,'Raw Data'!$N$2:$N$251) -> 3119.61 | C18: =SUMIF('Raw Data'!$F$2:$F$251,A18,'Raw Data'!$H$2:$H$251) -> 39 | D18: =COUNTIF('Raw Data'!$F$2:$F$251,A18) -> 14 | E18: Standard | F18: =SUMIF('Raw Data'!$L$2:$L$251,E18,'Raw Data'!$N$2:$N$251) -> 82357.54 | G18: =COUNTIF('Raw Data'!$L$2:$L$251,E18) -> 81 | H18: =AVERAGEIF('Raw Data'!$L$2:$L$251,E18,'Raw Data'!$N$2:$N$251) -> 1016.7598
A19: Desk | B19: =SUMIF('Raw Data'!$F$2:$F$251,A19,'Raw Data'!$N$2:$N$251) -> 23399.22 | C19: =SUMIF('Raw Data'!$F$2:$F$251,A19,'Raw Data'!$H$2:$H$251) -> 78 | D19: =COUNTIF('Raw Data'!$F$2:$F$251,A19) -> 26
A20: Headphones | B20: =SUMIF('Raw Data'!$F$2:$F$251,A20,'Raw Data'!$N$2:$N$251) -> 7049.53 | C20: =SUMIF('Raw Data'!$F$2:$F$251,A20,'Raw Data'!$H$2:$H$251) -> 47 | D20: =COUNTIF('Raw Data'!$F$2:$F$251,A20) -> 16
A21: Keyboard | B21: =SUMIF('Raw Data'!$F$2:$F$251,A21,'Raw Data'!$N$2:$N$251) -> 8009.11 | C21: =SUMIF('Raw Data'!$F$2:$F$251,A21,'Raw Data'!$H$2:$H$251) -> 89 | D21: =COUNTIF('Raw Data'!$F$2:$F$251,A21) -> 34
A22: Laptop | B22: =SUMIF('Raw Data'!$F$2:$F$251,A22,'Raw Data'!$N$2:$N$251) -> 67499.25 | C22: =SUMIF('Raw Data'!$F$2:$F$251,A22,'Raw Data'!$H$2:$H$251) -> 75 | D22: =COUNTIF('Raw Data'!$F$2:$F$251,A22) -> 24
A23: Monitor | B23: =SUMIF('Raw Data'!$F$2:$F$251,A23,'Raw Data'!$N$2:$N$251) -> 21999.12 | C23: =SUMIF('Raw Data'!$F$2:$F$251,A23,'Raw Data'!$H$2:$H$251) -> 88 | D23: =COUNTIF('Raw Data'!$F$2:$F$251,A23) -> 26
A24: Office Chair | B24: =SUMIF('Raw Data'!$F$2:$F$251,A24,'Raw Data'!$N$2:$N$251) -> 10399.48 | C24: =SUMIF('Raw Data'!$F$2:$F$251,A24,'Raw Data'!$H$2:$H$251) -> 52 | D24: =COUNTIF('Raw Data'!$F$2:$F$251,A24) -> 15
A25: Smartphone | B25: =SUMIF('Raw Data'!$F$2:$F$251,A25,'Raw Data'!$N$2:$N$251) -> 67199.04 | C25: =SUMIF('Raw Data'!$F$2:$F$251,A25,'Raw Data'!$H$2:$H$251) -> 96 | D25: =COUNTIF('Raw Data'!$F$2:$F$251,A25) -> 31
A27: 5. PAYMENT METHOD SUMMARY | E27: 6. MONTHLY TREND
A28: Payment Method | B28: Total Revenue | C28: Transactions | E28: Month | F28: Total Revenue | G28: Transactions
A29: Cash | B29: =SUMIF('Raw Data'!$J$2:$J$251,A29,'Raw Data'!$N$2:$N$251) -> 57427.79 | C29: =COUNTIF('Raw Data'!$J$2:$J$251,A29) -> 76 | E29: 45383 | F29: =SUMIFS('Raw Data'!$N$2:$N$251,'Raw Data'!$B$2:$B$251,">="&E29,'Raw Data'!$B$2:$B$251,"<"&EDATE(E29,1)) -> 20919.33 | G29: =COUNTIFS('Raw Data'!$B$2:$B$251,">="&E29,'Raw Data'!$B$2:$B$251,"<"&EDATE(E29,1)) -> 21
A30: Credit Card | B30: =SUMIF('Raw Data'!$J$2:$J$251,A30,'Raw Data'!$N$2:$N$251) -> 61447.96 | C30: =COUNTIF('Raw Data'!$J$2:$J$251,A30) -> 68 | E30: 45413 | F30: =SUMIFS('Raw Data'!$N$2:$N$251,'Raw Data'!$B$2:$B$251,">="&E30,'Raw Data'!$B$2:$B$251,"<"&EDATE(E30,1)) -> 17039.35 | G30: =COUNTIFS('Raw Data'!$B$2:$B$251,">="&E30,'Raw Data'!$B$2:$B$251,"<"&EDATE(E30,1)) -> 19
A31: Debit Card | B31: =SUMIF('Raw Data'!$J$2:$J$251,A31,'Raw Data'!$N$2:$N$251) -> 52118.31 | C31: =COUNTIF('Raw Data'!$J$2:$J$251,A31) -> 54 | E31: 45444 | F31: =SUMIFS('Raw Data'!$N$2:$N$251,'Raw Data'!$B$2:$B$251,">="&E31,'Raw Data'!$B$2:$B$251,"<"&EDATE(E31,1)) -> 19299.45 | G31: =COUNTIFS('Raw Data'!$B$2:$B$251,">="&E31,'Raw Data'!$B$2:$B$251,"<"&EDATE(E31,1)) -> 19
A32: PayPal | B32: =SUMIF('Raw Data'!$J$2:$J$251,A32,'Raw Data'!$N$2:$N$251) -> 58198.41 | C32: =COUNTIF('Raw Data'!$J$2:$J$251,A32) -> 52 | E32: 45474 | F32: =SUMIFS('Raw Data'!$N$2:$N$251,'Raw Data'!$B$2:$B$251,">="&E32,'Raw Data'!$B$2:$B$251,"<"&EDATE(E32,1)) -> 18479.4 | G32: =COUNTIFS('Raw Data'!$B$2:$B$251,">="&E32,'Raw Data'!$B$2:$B$251,"<"&EDATE(E32,1)) -> 24
E33: 45505 | F33: =SUMIFS('Raw Data'!$N$2:$N$251,'Raw Data'!$B$2:$B$251,">="&E33,'Raw Data'!$B$2:$B$251,"<"&EDATE(E33,1)) -> 15759.43 | G33: =COUNTIFS('Raw Data'!$B$2:$B$251,">="&E33,'Raw Data'!$B$2:$B$251,"<"&EDATE(E33,1)) -> 18
E34: 45536 | F34: =SUMIFS('Raw Data'!$N$2:$N$251,'Raw Data'!$B$2:$B$251,">="&E34,'Raw Data'!$B$2:$B$251,"<"&EDATE(E34,1)) -> 12989.51 | G34: =COUNTIFS('Raw Data'!$B$2:$B$251,">="&E34,'Raw Data'!$B$2:$B$251,"<"&EDATE(E34,1)) -> 19
E35: 45566 | F35: =SUMIFS('Raw Data'!$N$2:$N$251,'Raw Data'!$B$2:$B$251,">="&E35,'Raw Data'!$B$2:$B$251,"<"&EDATE(E35,1)) -> 20609.52 | G35: =COUNTIFS('Raw Data'!$B$2:$B$251,">="&E35,'Raw Data'!$B$2:$B$251,"<"&EDATE(E35,1)) -> 16
E36: 45597 | F36: =SUMIFS('Raw Data'!$N$2:$N$251,'Raw Data'!$B$2:$B$251,">="&E36,'Raw Data'!$B$2:$B$251,"<"&EDATE(E36,1)) -> 12309.44 | G36: =COUNTIFS('Raw Data'!$B$2:$B$251,">="&E36,'Raw Data'!$B$2:$B$251,"<"&EDATE(E36,1)) -> 17
E37: 45627 | F37: =SUMIFS('Raw Data'!$N$2:$N$251,'Raw Data'!$B$2:$B$251,">="&E37,'Raw Data'!$B$2:$B$251,"<"&EDATE(E37,1)) -> 23039.3 | G37: =COUNTIFS('Raw Data'!$B$2:$B$251,">="&E37,'Raw Data'!$B$2:$B$251,"<"&EDATE(E37,1)) -> 25
E38: 45658 | F38: =SUMIFS('Raw Data'!$N$2:$N$251,'Raw Data'!$B$2:$B$251,">="&E38,'Raw Data'!$B$2:$B$251,"<"&EDATE(E38,1)) -> 25799.15 | G38: =COUNTIFS('Raw Data'!$B$2:$B$251,">="&E38,'Raw Data'!$B$2:$B$251,"<"&EDATE(E38,1)) -> 26
E39: 45689 | F39: =SUMIFS('Raw Data'!$N$2:$N$251,'Raw Data'!$B$2:$B$251,">="&E39,'Raw Data'!$B$2:$B$251,"<"&EDATE(E39,1)) -> 16069.38 | G39: =COUNTIFS('Raw Data'!$B$2:$B$251,">="&E39,'Raw Data'!$B$2:$B$251,"<"&EDATE(E39,1)) -> 20
E40: 45717 | F40: =SUMIFS('Raw Data'!$N$2:$N$251,'Raw Data'!$B$2:$B$251,">="&E40,'Raw Data'!$B$2:$B$251,"<"&EDATE(E40,1)) -> 19899.38 | G40: =COUNTIFS('Raw Data'!$B$2:$B$251,">="&E40,'Raw Data'!$B$2:$B$251,"<"&EDATE(E40,1)) -> 19
E41: 45748 | F41: =SUMIFS('Raw Data'!$N$2:$N$251,'Raw Data'!$B$2:$B$251,">="&E41,'Raw Data'!$B$2:$B$251,"<"&EDATE(E41,1)) -> 6979.83 | G41: =COUNTIFS('Raw Data'!$B$2:$B$251,">="&E41,'Raw Data'!$B$2:$B$251,"<"&EDATE(E41,1)) -> 7

Sheet Visualizations
A1: VISUALIZATION STUDIO | CHARTS & TRENDS
A3: Revenue by Category | D3: Revenue by Region | G3: Units by Product | J3: Monthly Revenue
A4: =Analysis!D4 -> Appliances | B4: =Analysis!E4 -> 8338.74 | D4: =Analysis!G4 -> Central | E4: =Analysis!H4 -> 41288.34 | G4: =Analysis!A16 -> Blender | H4: =Analysis!B16 -> 87 | J4: =Analysis!J4 -> 2024-04 | K4: =Analysis!K4 -> 20919.33
A5: =Analysis!D5 -> Electronics | B5: =Analysis!E5 -> 171756.05 | D5: =Analysis!G5 -> East | E5: =Analysis!H5 -> 59288.39 | G5: =Analysis!A17 -> Bookshelf | H5: =Analysis!B17 -> 102 | J5: =Analysis!J5 -> 2024-05 | K5: =Analysis!K5 -> 17039.35
A6: =Analysis!D6 -> Furniture | B6: =Analysis!E6 -> 49097.68 | D6: =Analysis!G6 -> North | E6: =Analysis!H6 -> 50808.31 | G6: =Analysis!A18 -> Coffee Maker | H6: =Analysis!B18 -> 39 | J6: =Analysis!J6 -> 2024-06 | K6: =Analysis!K6 -> 19299.45
D7: =Analysis!G7 -> South | E7: =Analysis!H7 -> 36398.75 | G7: =Analysis!A19 -> Desk | H7: =Analysis!B19 -> 78 | J7: =Analysis!J7 -> 2024-07 | K7: =Analysis!K7 -> 18479.4
D8: =Analysis!G8 -> West | E8: =Analysis!H8 -> 41408.68 | G8: =Analysis!A20 -> Headphones | H8: =Analysis!B20 -> 47 | J8: =Analysis!J8 -> 2024-08 | K8: =Analysis!K8 -> 15759.43
G9: =Analysis!A21 -> Keyboard | H9: =Analysis!B21 -> 89 | J9: =Analysis!J9 -> 2024-09 | K9: =Analysis!K9 -> 12989.51
G10: =Analysis!A22 -> Laptop | H10: =Analysis!B22 -> 75 | J10: =Analysis!J10 -> 2024-10 | K10: =Analysis!K10 -> 20609.52
G11: =Analysis!A23 -> Monitor | H11: =Analysis!B23 -> 88 | J11: =Analysis!J11 -> 2024-11 | K11: =Analysis!K11 -> 12309.44
G12: =Analysis!A24 -> Office Chair | H12: =Analysis!B24 -> 52 | J12: =Analysis!J12 -> 2024-12 | K12: =Analysis!K12 -> 23039.3
G13: =Analysis!A25 -> Smartphone | H13: =Analysis!B25 -> 96 | J13: =Analysis!J13 -> 2025-01 | K13: =Analysis!K13 -> 25799.15
J14: =Analysis!J14 -> 2025-02 | K14: =Analysis!K14 -> 16069.38
J15: =Analysis!J15 -> 2025-03 | K15: =Analysis!K15 -> 19899.38
J16: =Analysis!J16 -> 2025-04 | K16: =Analysis!K16 -> 6979.83

Sheet What-If & Regression
A1: WHAT-IF ANALYSIS & REGRESSION WORKBENCH
A3: Scenario | B3: Quantity multiplier | C3: Price multiplier | D3: Projected revenue
A4: Conservative | B4: 0.9 | C4: 0.95 | D4: =SUM('Raw Data'!H2:H251)*B4*SUM('Raw Data'!I2:I251)*C4/COUNT('Raw Data'!I2:I251) -> 191000.6
A5: Base case | B5: 1 | C5: 1 | D5: =SUM('Raw Data'!H2:H251)*B5*SUM('Raw Data'!I2:I251)*C5/COUNT('Raw Data'!I2:I251) -> 223392.51
A6: Growth | B6: 1.15 | C6: 1.05 | D6: =SUM('Raw Data'!H2:H251)*B6*SUM('Raw Data'!I2:I251)*C6/COUNT('Raw Data'!I2:I251) -> 269746.46
A9: Goal Seek setup
A10: Target revenue | B10: 50000
A11: Quantity multiplier (changing cell) | B11: 1
A12: Projected revenue | B12: =SUM('Raw Data'!H2:H251)*B11*SUM('Raw Data'!I2:I251)*1/COUNT('Raw Data'!I2:I251) -> 223392.51
A16: Linear regression (monthly revenue vs month index)
A17: Metric | B17: Formula / result
A18: Slope | B18: =SLOPE(Analysis!K4:K16,ROW(Analysis!K4:K16)-ROW(Analysis!K4)+1) -> -255.04511
A19: Intercept | B19: =INTERCEPT(Analysis!K4:K16,ROW(Analysis!K4:K16)-ROW(Analysis!K4)+1) -> 19415.506
A20: R-squared | B20: =RSQ(Analysis!K4:K16,ROW(Analysis!K4:K16)-ROW(Analysis!K4)+1) -> 0.040281042
A22: Data Analysis ToolPak steps
